{
    "expectedSellerId": 1,
    "owned": true,
    "isPurchasable": false,
    "id": 16630147,
    "itemType": "Asset",
    "assetType": 41,
    "name": "Beautiful Hair for Beautiful People",
    "description": "You are all beautiful to me.",
    "productId": 2843017,
    "genres": [
        "All"
    ],
    "itemStatus": [],
    "itemRestrictions": [],
    "creatorHasVerifiedBadge": true,
    "creatorType": "User",
    "creatorTargetId": 1,
    "creatorName": "Roblox",
    "price": 95,
    "favoriteCount": 1708165,
    "offSaleDeadline": null,
    "saleLocationType": "NotApplicable"
}